lock_and_key/__about__.py
lock_and_key/__init__.py
lock_and_key/cli.py
lock_and_key/main.py
lock_and_key/config/__init__.py
lock_and_key/config/settings.py
lock_and_key/core/__init__.py
lock_and_key/core/scanner.py
lock_and_key/core/ui.py
lock_and_key/providers/__init__.py
lock_and_key/providers/azure.py
lock_and_key/providers/gcp.py
lock_and_key/providers/aws/__init__.py
lock_and_key/providers/aws/aws_policy_collector.py
lock_and_key/providers/aws/aws_provider.py
lock_and_key/providers/aws/resources/__init__.py
lock_and_key/providers/aws/resources/base.py
lock_and_key/providers/aws/resources/iam.py
lock_and_key/providers/aws/resources/iam_policy_analyzer.py
lock_and_key/types/__init__.py
lock_and_key/types/base.py
lock_and_key/types/credentials.py
lock_and_key/types/exceptions.py
lock_and_key/types/scan_results.py
lock_and_key-1.0.4.dist-info/METADATA
lock_and_key-1.0.4.dist-info/WHEEL
lock_and_key-1.0.4.dist-info/entry_points.txt
lock_and_key-1.0.4.dist-info/licenses/LICENSE.txt
lock_and_key-1.0.4.dist-info/RECORD
