Metadata-Version: 2.4
Name: lock-and-key
Version: 1.0.4
Summary: Comprehensive cloud security scanner for IAM and resource-based policies
Project-URL: Documentation, https://thewintershadow.github.io/Lock-And-Key/
Project-URL: Homepage, https://github.com/TheWinterShadow/lock-and-key
Project-URL: Repository, https://github.com/TheWinterShadow/lock-and-key
Project-URL: Issues, https://github.com/TheWinterShadow/lock-and-key/issues
Project-URL: Changelog, https://github.com/TheWinterShadow/lock-and-key/blob/main/CHANGELOG.md
Author-email: WinterShadow <wolf@cyberwolf.dev>
License-Expression: MIT
License-File: LICENSE.txt
Keywords: aws,azure,cloud,gcp,iam,scanner,security
Classifier: Development Status :: 4 - Beta
Classifier: Intended Audience :: Developers
Classifier: Intended Audience :: System Administrators
Classifier: License :: OSI Approved :: MIT License
Classifier: Operating System :: OS Independent
Classifier: Programming Language :: Python
Classifier: Programming Language :: Python :: 3.9
Classifier: Programming Language :: Python :: 3.10
Classifier: Programming Language :: Python :: 3.11
Classifier: Programming Language :: Python :: 3.12
Classifier: Programming Language :: Python :: 3.13
Classifier: Programming Language :: Python :: Implementation :: CPython
Classifier: Programming Language :: Python :: Implementation :: PyPy
Classifier: Topic :: Security
Classifier: Topic :: Software Development :: Libraries :: Python Modules
Classifier: Topic :: System :: Systems Administration
Requires-Python: >=3.9
Requires-Dist: boto3>=1.40.0
Requires-Dist: botocore>=1.40.0
Requires-Dist: click>=8.0.0
Requires-Dist: pydantic>=2.0.0
Requires-Dist: rich>=13.0.0
Provides-Extra: all
Requires-Dist: bandit>=1.7.0; extra == 'all'
Requires-Dist: black>=23.0.0; extra == 'all'
Requires-Dist: boto3-stubs>=1.40.0; extra == 'all'
Requires-Dist: flake8>=6.0.0; extra == 'all'
Requires-Dist: furo>=2.0.0; extra == 'all'
Requires-Dist: isort>=5.12.0; extra == 'all'
Requires-Dist: mypy-boto3-dynamodb>=1.40.0; extra == 'all'
Requires-Dist: mypy-boto3-iam>=1.40.0; extra == 'all'
Requires-Dist: mypy-boto3-lambda>=1.40.0; extra == 'all'
Requires-Dist: mypy-boto3-s3>=1.40.0; extra == 'all'
Requires-Dist: mypy-boto3-sns>=1.40.0; extra == 'all'
Requires-Dist: mypy-boto3-sqs>=1.40.0; extra == 'all'
Requires-Dist: mypy-boto3-sts>=1.40.0; extra == 'all'
Requires-Dist: mypy>=1.0.0; extra == 'all'
Requires-Dist: myst-parser>=2.0.0; extra == 'all'
Requires-Dist: pytest-cov>=4.0.0; extra == 'all'
Requires-Dist: pytest>=7.0.0; extra == 'all'
Requires-Dist: sphinx>=5.0.0; extra == 'all'
Provides-Extra: aws
Requires-Dist: boto3-stubs>=1.40.0; extra == 'aws'
Requires-Dist: mypy-boto3-dynamodb>=1.40.0; extra == 'aws'
Requires-Dist: mypy-boto3-iam>=1.40.0; extra == 'aws'
Requires-Dist: mypy-boto3-lambda>=1.40.0; extra == 'aws'
Requires-Dist: mypy-boto3-s3>=1.40.0; extra == 'aws'
Requires-Dist: mypy-boto3-sns>=1.40.0; extra == 'aws'
Requires-Dist: mypy-boto3-sqs>=1.40.0; extra == 'aws'
Requires-Dist: mypy-boto3-sts>=1.40.0; extra == 'aws'
Provides-Extra: dev
Requires-Dist: bandit>=1.7.0; extra == 'dev'
Requires-Dist: black>=23.0.0; extra == 'dev'
Requires-Dist: flake8>=6.0.0; extra == 'dev'
Requires-Dist: isort>=5.12.0; extra == 'dev'
Requires-Dist: mypy>=1.0.0; extra == 'dev'
Requires-Dist: pytest-cov>=4.0.0; extra == 'dev'
Requires-Dist: pytest>=7.0.0; extra == 'dev'
Provides-Extra: docs
Requires-Dist: furo>=2023.0.0; extra == 'docs'
Requires-Dist: myst-parser>=2.0.0; extra == 'docs'
Requires-Dist: sphinx>=5.0.0; extra == 'docs'
